functor/__init__.py
functor/__init__.pyi
functor/core.py
functor/utils/__init__.py
functor/utils/proxy.py
functor/utils/typing.py
functor-0.0.1b1.dev0.dist-info/licenses/LICENSE
functor-0.0.1b1.dev0.dist-info/METADATA
functor-0.0.1b1.dev0.dist-info/WHEEL
functor-0.0.1b1.dev0.dist-info/top_level.txt
functor-0.0.1b1.dev0.dist-info/RECORD
