Metadata-Version: 2.4
Name: functor
Version: 0.0.1b1.dev0
Summary: The `functor` package uses Python black magic to turn functions into objects (functors), letting them access their own instance via `functor.self`.
Author-email: Caewinix <Caewinix@yeah.net>
Project-URL: Homepage, https://github.com/Caewinix/functor
Project-URL: Bug Tracker, https://github.com/Caewinix/functor/issues
Classifier: Programming Language :: Python :: 3
Classifier: License :: OSI Approved :: MIT License
Classifier: Operating System :: OS Independent
Requires-Python: >=3.6
License-File: LICENSE
Requires-Dist: typing_extensions
Dynamic: license-file
